ardent/__init__.py
ardent/__version__.py
ardent/file_io.py
ardent/imageData.py
ardent/transform.py
ardent/utilities.py
ardent/visualization.py
ardent/lddmm/__init__.py
ardent/lddmm/_lddmm.py
ardent/lddmm/_lddmm_utilities.py
ardent/lddmm/test_lddmm.py
ardent/lddmm/test_lddmm_utilities.py
ardent/preprocessing/__init__.py
ardent/preprocessing/bias_and_artifact_correction.py
ardent/preprocessing/modify_velocity_fields.py
ardent/preprocessing/normalization.py
ardent/preprocessing/resampling.py
ardent/preprocessing/sliced_data.py
ardent/presets/__init__.py
ardent/presets/batch_preprocessing.py
ardent/presets/registration_parameters.py
tests/__init__.py
tests/archived_test_imageData.py
tests/test_utilities.py
ardent-1.0.3.dist-info/LICENSE
ardent-1.0.3.dist-info/METADATA
ardent-1.0.3.dist-info/WHEEL
ardent-1.0.3.dist-info/top_level.txt
ardent-1.0.3.dist-info/RECORD
