Metadata-Version: 2.1
Name: ardent
Version: 1.0.3
Summary: A tool for nonlinear image registration.
Home-page: https://github.com/neurodata/ardent
Author: Devin Crowley
Author-email: devin.g.crowley@gmail.com
License: Apache License 2.0
Platform: UNKNOWN
Classifier: Development Status :: 4 - Beta
Classifier: Intended Audience :: Science/Research
Classifier: Topic :: Scientific/Engineering :: Mathematics
Classifier: License :: OSI Approved :: Apache Software License
Classifier: Programming Language :: Python :: 3
Classifier: Programming Language :: Python :: 3.6
Classifier: Programming Language :: Python :: 3.7
Requires-Python: >=3.6
Requires-Dist: numpy (>=1.16.3)
Requires-Dist: matplotlib (>=3.1.0)
Requires-Dist: simpleitk (>=1.2.0)
Requires-Dist: scipy (>=1.3.0)
Requires-Dist: nibabel (>=2.4.1)
Requires-Dist: nilearn (>=0.5.2)
Requires-Dist: scikit-learn (>=0.21.2)
Requires-Dist: scikit-image (>=0.16.2)
